arcade_stripe_api/__init__.py
arcade_stripe_api/tools/__init__.py
arcade_stripe_api/wrapper_tools/DeleteAccountPerson.json
arcade_stripe_api/wrapper_tools/DeleteAccountPersonRelationship.json
arcade_stripe_api/wrapper_tools/DeleteApplePayDomain.json
arcade_stripe_api/wrapper_tools/DeleteCustomerTaxId.json
arcade_stripe_api/wrapper_tools/DeleteExternalAccount.json
arcade_stripe_api/wrapper_tools/DeleteExternalBankAccount.json
arcade_stripe_api/wrapper_tools/DeleteInvoiceDraft.json
arcade_stripe_api/wrapper_tools/DeleteInvoiceItem.json
arcade_stripe_api/wrapper_tools/DeleteProductFeature.json
arcade_stripe_api/wrapper_tools/DeleteStripeConnectedAccount.json
arcade_stripe_api/wrapper_tools/DeleteStripeCoupon.json
arcade_stripe_api/wrapper_tools/DeleteStripeCustomer.json
arcade_stripe_api/wrapper_tools/DeleteStripePlan.json
arcade_stripe_api/wrapper_tools/DeleteStripeProduct.json
arcade_stripe_api/wrapper_tools/DeleteStripeValueList.json
arcade_stripe_api/wrapper_tools/DeleteStripeWebhookEndpoint.json
arcade_stripe_api/wrapper_tools/DeleteTaxId.json
arcade_stripe_api/wrapper_tools/DeleteTerminalConfiguration.json
arcade_stripe_api/wrapper_tools/DeleteTerminalLocation.json
arcade_stripe_api/wrapper_tools/DeleteTerminalReader.json
arcade_stripe_api/wrapper_tools/DeleteTestClock.json
arcade_stripe_api/wrapper_tools/DownloadQuotePdf.json
arcade_stripe_api/wrapper_tools/GetAccountCapabilities.json
arcade_stripe_api/wrapper_tools/GetAccountCapabilityDetails.json
arcade_stripe_api/wrapper_tools/GetAccountOwners.json
arcade_stripe_api/wrapper_tools/GetActiveEntitlements.json
arcade_stripe_api/wrapper_tools/GetApplicationFeeRefunds.json
arcade_stripe_api/wrapper_tools/GetBalanceSettings.json
arcade_stripe_api/wrapper_tools/GetBalanceTransactionById.json
arcade_stripe_api/wrapper_tools/GetBillingAlert.json
arcade_stripe_api/wrapper_tools/GetBillingAlerts.json
arcade_stripe_api/wrapper_tools/GetBillingCreditGrants.json
arcade_stripe_api-1.0.0.dist-info/METADATA
arcade_stripe_api-1.0.0.dist-info/WHEEL
arcade_stripe_api-1.0.0.dist-info/licenses/LICENSE
arcade_stripe_api-1.0.0.dist-info/RECORD
